[
  {
    "model": "admin.logentry",
    "pk": 1,
    "fields": {
      "action_time": "2021-07-17T16:49:56.526Z",
      "user": 3,
      "content_type": 6,
      "object_id": "1",
      "object_repr": "md sohan",
      "action_flag": 1,
      "change_message": "[{\"added\": {}}, {\"added\": {\"name\": \"product images\", \"object\": \"md sohan\"}}, {\"added\": {\"name\": \"product images\", \"object\": \"md sohan\"}}, {\"added\": {\"name\": \"product images\", \"object\": \"md sohan\"}}]"
    }
  },
  {
    "model": "admin.logentry",
    "pk": 2,
    "fields": {
      "action_time": "2021-07-23T16:09:44.924Z",
      "user": 3,
      "content_type": 6,
      "object_id": "2",
      "object_repr": "one",
      "action_flag": 1,
      "change_message": "[{\"added\": {}}, {\"added\": {\"name\": \"product images\", \"object\": \"one\"}}, {\"added\": {\"name\": \"product images\", \"object\": \"one\"}}, {\"added\": {\"name\": \"product images\", \"object\": \"one\"}}]"
    }
  },
  {
    "model": "admin.logentry",
    "pk": 3,
    "fields": {
      "action_time": "2021-07-23T16:10:15.606Z",
      "user": 3,
      "content_type": 6,
      "object_id": "3",
      "object_repr": "two",
      "action_flag": 1,
      "change_message": "[{\"added\": {}}, {\"added\": {\"name\": \"product images\", \"object\": \"two\"}}, {\"added\": {\"name\": \"product images\", \"object\": \"two\"}}, {\"added\": {\"name\": \"product images\", \"object\": \"two\"}}]"
    }
  },
  {
    "model": "admin.logentry",
    "pk": 4,
    "fields": {
      "action_time": "2021-07-23T16:10:41.563Z",
      "user": 3,
      "content_type": 6,
      "object_id": "4",
      "object_repr": "three",
      "action_flag": 1,
      "change_message": "[{\"added\": {}}, {\"added\": {\"name\": \"product images\", \"object\": \"three\"}}, {\"added\": {\"name\": \"product images\", \"object\": \"three\"}}, {\"added\": {\"name\": \"product images\", \"object\": \"three\"}}]"
    }
  },
  {
    "model": "admin.logentry",
    "pk": 5,
    "fields": {
      "action_time": "2021-07-23T16:11:11.982Z",
      "user": 3,
      "content_type": 6,
      "object_id": "5",
      "object_repr": "four",
      "action_flag": 1,
      "change_message": "[{\"added\": {}}, {\"added\": {\"name\": \"product images\", \"object\": \"four\"}}, {\"added\": {\"name\": \"product images\", \"object\": \"four\"}}, {\"added\": {\"name\": \"product images\", \"object\": \"four\"}}]"
    }
  },
  {
    "model": "admin.logentry",
    "pk": 6,
    "fields": {
      "action_time": "2021-07-23T16:11:39.662Z",
      "user": 3,
      "content_type": 6,
      "object_id": "6",
      "object_repr": "seven",
      "action_flag": 1,
      "change_message": "[{\"added\": {}}, {\"added\": {\"name\": \"product images\", \"object\": \"seven\"}}, {\"added\": {\"name\": \"product images\", \"object\": \"seven\"}}, {\"added\": {\"name\": \"product images\", \"object\": \"seven\"}}]"
    }
  },
  {
    "model": "admin.logentry",
    "pk": 7,
    "fields": {
      "action_time": "2021-07-23T16:35:18.161Z",
      "user": 3,
      "content_type": 6,
      "object_id": "2",
      "object_repr": "one",
      "action_flag": 2,
      "change_message": "[{\"changed\": {\"fields\": [\"Category\"]}}]"
    }
  },
  {
    "model": "admin.logentry",
    "pk": 8,
    "fields": {
      "action_time": "2021-07-24T08:26:18.564Z",
      "user": 3,
      "content_type": 29,
      "object_id": "1",
      "object_repr": "ABC_50",
      "action_flag": 1,
      "change_message": "[{\"added\": {}}]"
    }
  },
  {
    "model": "admin.logentry",
    "pk": 9,
    "fields": {
      "action_time": "2021-07-24T08:46:33.886Z",
      "user": 3,
      "content_type": 29,
      "object_id": "1",
      "object_repr": "ABC_50",
      "action_flag": 2,
      "change_message": "[{\"changed\": {\"fields\": [\"Valid to\"]}}]"
    }
  },
  {
    "model": "admin.logentry",
    "pk": 10,
    "fields": {
      "action_time": "2021-07-24T08:47:55.405Z",
      "user": 3,
      "content_type": 29,
      "object_id": "1",
      "object_repr": "ABC_50",
      "action_flag": 2,
      "change_message": "[{\"changed\": {\"fields\": [\"Valid to\"]}}]"
    }
  },
  {
    "model": "admin.logentry",
    "pk": 11,
    "fields": {
      "action_time": "2021-07-24T08:57:37.081Z",
      "user": 3,
      "content_type": 10,
      "object_id": "2",
      "object_repr": "Order object (2)",
      "action_flag": 2,
      "change_message": "[{\"changed\": {\"fields\": [\"Coupon\"]}}]"
    }
  },
  {
    "model": "admin.logentry",
    "pk": 12,
    "fields": {
      "action_time": "2021-07-24T08:58:39.430Z",
      "user": 3,
      "content_type": 10,
      "object_id": "2",
      "object_repr": "Order object (2)",
      "action_flag": 2,
      "change_message": "[{\"changed\": {\"fields\": [\"Coupon\"]}}]"
    }
  },
  {
    "model": "admin.logentry",
    "pk": 13,
    "fields": {
      "action_time": "2021-07-24T09:19:47.112Z",
      "user": 3,
      "content_type": 11,
      "object_id": "1",
      "object_repr": "",
      "action_flag": 1,
      "change_message": "[{\"added\": {}}]"
    }
  },
  {
    "model": "admin.logentry",
    "pk": 14,
    "fields": {
      "action_time": "2021-07-24T09:22:36.563Z",
      "user": 3,
      "content_type": 10,
      "object_id": "2",
      "object_repr": "Order object (2)",
      "action_flag": 2,
      "change_message": "[{\"changed\": {\"fields\": [\"Address\"]}}]"
    }
  },
  {
    "model": "admin.logentry",
    "pk": 15,
    "fields": {
      "action_time": "2021-07-24T09:23:32.767Z",
      "user": 3,
      "content_type": 30,
      "object_id": "1",
      "object_repr": "inside_dhaka",
      "action_flag": 1,
      "change_message": "[{\"added\": {}}]"
    }
  },
  {
    "model": "admin.logentry",
    "pk": 16,
    "fields": {
      "action_time": "2021-07-24T09:23:44.621Z",
      "user": 3,
      "content_type": 30,
      "object_id": "2",
      "object_repr": "outside_dhaka",
      "action_flag": 1,
      "change_message": "[{\"added\": {}}]"
    }
  },
  {
    "model": "admin.logentry",
    "pk": 17,
    "fields": {
      "action_time": "2021-07-24T09:26:43.522Z",
      "user": 3,
      "content_type": 10,
      "object_id": "2",
      "object_repr": "Order object (2)",
      "action_flag": 2,
      "change_message": "[{\"changed\": {\"fields\": [\"Coupon\"]}}]"
    }
  },
  {
    "model": "admin.logentry",
    "pk": 18,
    "fields": {
      "action_time": "2021-07-24T09:27:06.106Z",
      "user": 3,
      "content_type": 10,
      "object_id": "2",
      "object_repr": "Order object (2)",
      "action_flag": 2,
      "change_message": "[{\"changed\": {\"fields\": [\"Coupon\"]}}]"
    }
  },
  {
    "model": "admin.logentry",
    "pk": 19,
    "fields": {
      "action_time": "2021-07-24T09:28:21.379Z",
      "user": 3,
      "content_type": 10,
      "object_id": "2",
      "object_repr": "Order object (2)",
      "action_flag": 2,
      "change_message": "[{\"changed\": {\"fields\": [\"Address\"]}}]"
    }
  },
  {
    "model": "admin.logentry",
    "pk": 20,
    "fields": {
      "action_time": "2021-07-24T10:04:55.678Z",
      "user": 3,
      "content_type": 10,
      "object_id": "2",
      "object_repr": "Order object (2)",
      "action_flag": 2,
      "change_message": "[{\"changed\": {\"fields\": [\"Coupon\"]}}]"
    }
  },
  {
    "model": "admin.logentry",
    "pk": 21,
    "fields": {
      "action_time": "2021-07-24T10:13:20.670Z",
      "user": 3,
      "content_type": 10,
      "object_id": "2",
      "object_repr": "Order object (2)",
      "action_flag": 2,
      "change_message": "[{\"changed\": {\"fields\": [\"Coupon\"]}}]"
    }
  },
  {
    "model": "admin.logentry",
    "pk": 22,
    "fields": {
      "action_time": "2021-07-24T10:13:41.414Z",
      "user": 3,
      "content_type": 10,
      "object_id": "2",
      "object_repr": "Order object (2)",
      "action_flag": 2,
      "change_message": "[{\"changed\": {\"fields\": [\"Coupon\"]}}]"
    }
  },
  {
    "model": "admin.logentry",
    "pk": 23,
    "fields": {
      "action_time": "2021-07-24T10:14:33.938Z",
      "user": 3,
      "content_type": 10,
      "object_id": "2",
      "object_repr": "Order object (2)",
      "action_flag": 2,
      "change_message": "[{\"changed\": {\"fields\": [\"Coupon\"]}}]"
    }
  },
  {
    "model": "admin.logentry",
    "pk": 24,
    "fields": {
      "action_time": "2021-07-24T10:14:50.722Z",
      "user": 3,
      "content_type": 10,
      "object_id": "2",
      "object_repr": "Order object (2)",
      "action_flag": 2,
      "change_message": "[{\"changed\": {\"fields\": [\"Coupon\"]}}]"
    }
  },
  {
    "model": "admin.logentry",
    "pk": 25,
    "fields": {
      "action_time": "2021-07-25T05:33:24.190Z",
      "user": 3,
      "content_type": 10,
      "object_id": "2",
      "object_repr": "Order object (2)",
      "action_flag": 3,
      "change_message": ""
    }
  },
  {
    "model": "admin.logentry",
    "pk": 26,
    "fields": {
      "action_time": "2021-07-25T05:42:55.729Z",
      "user": 3,
      "content_type": 10,
      "object_id": "3",
      "object_repr": "Order object (3)",
      "action_flag": 3,
      "change_message": ""
    }
  },
  {
    "model": "admin.logentry",
    "pk": 27,
    "fields": {
      "action_time": "2021-07-25T05:42:55.762Z",
      "user": 3,
      "content_type": 10,
      "object_id": "1",
      "object_repr": "Order object (1)",
      "action_flag": 3,
      "change_message": ""
    }
  },
  {
    "model": "admin.logentry",
    "pk": 28,
    "fields": {
      "action_time": "2021-07-25T05:44:41.967Z",
      "user": 3,
      "content_type": 12,
      "object_id": "20",
      "object_repr": "Cart object (20)",
      "action_flag": 3,
      "change_message": ""
    }
  },
  {
    "model": "admin.logentry",
    "pk": 29,
    "fields": {
      "action_time": "2021-07-25T05:44:42.011Z",
      "user": 3,
      "content_type": 12,
      "object_id": "19",
      "object_repr": "Cart object (19)",
      "action_flag": 3,
      "change_message": ""
    }
  },
  {
    "model": "admin.logentry",
    "pk": 30,
    "fields": {
      "action_time": "2021-07-25T05:44:42.046Z",
      "user": 3,
      "content_type": 12,
      "object_id": "18",
      "object_repr": "Cart object (18)",
      "action_flag": 3,
      "change_message": ""
    }
  },
  {
    "model": "admin.logentry",
    "pk": 31,
    "fields": {
      "action_time": "2021-07-25T05:44:42.081Z",
      "user": 3,
      "content_type": 12,
      "object_id": "17",
      "object_repr": "Cart object (17)",
      "action_flag": 3,
      "change_message": ""
    }
  },
  {
    "model": "admin.logentry",
    "pk": 32,
    "fields": {
      "action_time": "2021-07-25T05:44:42.139Z",
      "user": 3,
      "content_type": 12,
      "object_id": "16",
      "object_repr": "Cart object (16)",
      "action_flag": 3,
      "change_message": ""
    }
  },
  {
    "model": "admin.logentry",
    "pk": 33,
    "fields": {
      "action_time": "2021-07-25T05:44:42.175Z",
      "user": 3,
      "content_type": 12,
      "object_id": "15",
      "object_repr": "Cart object (15)",
      "action_flag": 3,
      "change_message": ""
    }
  },
  {
    "model": "admin.logentry",
    "pk": 34,
    "fields": {
      "action_time": "2021-07-25T05:44:42.211Z",
      "user": 3,
      "content_type": 12,
      "object_id": "14",
      "object_repr": "Cart object (14)",
      "action_flag": 3,
      "change_message": ""
    }
  },
  {
    "model": "admin.logentry",
    "pk": 35,
    "fields": {
      "action_time": "2021-07-25T05:44:42.246Z",
      "user": 3,
      "content_type": 12,
      "object_id": "13",
      "object_repr": "Cart object (13)",
      "action_flag": 3,
      "change_message": ""
    }
  },
  {
    "model": "admin.logentry",
    "pk": 36,
    "fields": {
      "action_time": "2021-07-25T05:44:42.282Z",
      "user": 3,
      "content_type": 12,
      "object_id": "12",
      "object_repr": "Cart object (12)",
      "action_flag": 3,
      "change_message": ""
    }
  },
  {
    "model": "admin.logentry",
    "pk": 37,
    "fields": {
      "action_time": "2021-07-25T05:44:42.317Z",
      "user": 3,
      "content_type": 12,
      "object_id": "11",
      "object_repr": "Cart object (11)",
      "action_flag": 3,
      "change_message": ""
    }
  },
  {
    "model": "admin.logentry",
    "pk": 38,
    "fields": {
      "action_time": "2021-07-25T05:44:42.353Z",
      "user": 3,
      "content_type": 12,
      "object_id": "10",
      "object_repr": "Cart object (10)",
      "action_flag": 3,
      "change_message": ""
    }
  },
  {
    "model": "admin.logentry",
    "pk": 39,
    "fields": {
      "action_time": "2021-07-25T05:44:42.410Z",
      "user": 3,
      "content_type": 12,
      "object_id": "9",
      "object_repr": "Cart object (9)",
      "action_flag": 3,
      "change_message": ""
    }
  },
  {
    "model": "admin.logentry",
    "pk": 40,
    "fields": {
      "action_time": "2021-07-25T05:44:42.491Z",
      "user": 3,
      "content_type": 12,
      "object_id": "8",
      "object_repr": "Cart object (8)",
      "action_flag": 3,
      "change_message": ""
    }
  },
  {
    "model": "admin.logentry",
    "pk": 41,
    "fields": {
      "action_time": "2021-07-25T05:44:42.538Z",
      "user": 3,
      "content_type": 12,
      "object_id": "7",
      "object_repr": "Cart object (7)",
      "action_flag": 3,
      "change_message": ""
    }
  },
  {
    "model": "admin.logentry",
    "pk": 42,
    "fields": {
      "action_time": "2021-07-25T05:44:42.606Z",
      "user": 3,
      "content_type": 12,
      "object_id": "2",
      "object_repr": "Cart object (2)",
      "action_flag": 3,
      "change_message": ""
    }
  },
  {
    "model": "admin.logentry",
    "pk": 43,
    "fields": {
      "action_time": "2021-07-25T05:44:51.363Z",
      "user": 3,
      "content_type": 10,
      "object_id": "4",
      "object_repr": "Order object (4)",
      "action_flag": 3,
      "change_message": ""
    }
  },
  {
    "model": "admin.logentry",
    "pk": 44,
    "fields": {
      "action_time": "2021-07-25T05:49:32.982Z",
      "user": 3,
      "content_type": 12,
      "object_id": "27",
      "object_repr": "Cart object (27)",
      "action_flag": 3,
      "change_message": ""
    }
  },
  {
    "model": "admin.logentry",
    "pk": 45,
    "fields": {
      "action_time": "2021-07-25T05:49:33.022Z",
      "user": 3,
      "content_type": 12,
      "object_id": "26",
      "object_repr": "Cart object (26)",
      "action_flag": 3,
      "change_message": ""
    }
  },
  {
    "model": "admin.logentry",
    "pk": 46,
    "fields": {
      "action_time": "2021-07-25T05:49:33.060Z",
      "user": 3,
      "content_type": 12,
      "object_id": "25",
      "object_repr": "Cart object (25)",
      "action_flag": 3,
      "change_message": ""
    }
  },
  {
    "model": "admin.logentry",
    "pk": 47,
    "fields": {
      "action_time": "2021-07-25T05:49:33.094Z",
      "user": 3,
      "content_type": 12,
      "object_id": "24",
      "object_repr": "Cart object (24)",
      "action_flag": 3,
      "change_message": ""
    }
  },
  {
    "model": "admin.logentry",
    "pk": 48,
    "fields": {
      "action_time": "2021-07-25T05:49:33.130Z",
      "user": 3,
      "content_type": 12,
      "object_id": "23",
      "object_repr": "Cart object (23)",
      "action_flag": 3,
      "change_message": ""
    }
  },
  {
    "model": "admin.logentry",
    "pk": 49,
    "fields": {
      "action_time": "2021-07-25T05:49:33.165Z",
      "user": 3,
      "content_type": 12,
      "object_id": "22",
      "object_repr": "Cart object (22)",
      "action_flag": 3,
      "change_message": ""
    }
  },
  {
    "model": "admin.logentry",
    "pk": 50,
    "fields": {
      "action_time": "2021-07-25T05:49:33.201Z",
      "user": 3,
      "content_type": 12,
      "object_id": "21",
      "object_repr": "Cart object (21)",
      "action_flag": 3,
      "change_message": ""
    }
  },
  {
    "model": "admin.logentry",
    "pk": 51,
    "fields": {
      "action_time": "2021-07-25T05:49:42.704Z",
      "user": 3,
      "content_type": 10,
      "object_id": "6",
      "object_repr": "Order object (6)",
      "action_flag": 3,
      "change_message": ""
    }
  },
  {
    "model": "admin.logentry",
    "pk": 52,
    "fields": {
      "action_time": "2021-07-25T05:50:06.539Z",
      "user": 3,
      "content_type": 10,
      "object_id": "5",
      "object_repr": "Order object (5)",
      "action_flag": 3,
      "change_message": ""
    }
  },
  {
    "model": "admin.logentry",
    "pk": 53,
    "fields": {
      "action_time": "2021-07-25T05:50:31.696Z",
      "user": 3,
      "content_type": 10,
      "object_id": "7",
      "object_repr": "Order object (7)",
      "action_flag": 3,
      "change_message": ""
    }
  },
  {
    "model": "admin.logentry",
    "pk": 54,
    "fields": {
      "action_time": "2021-07-25T07:00:33.598Z",
      "user": 3,
      "content_type": 12,
      "object_id": "31",
      "object_repr": "Cart object (31)",
      "action_flag": 3,
      "change_message": ""
    }
  },
  {
    "model": "admin.logentry",
    "pk": 55,
    "fields": {
      "action_time": "2021-07-25T07:00:33.678Z",
      "user": 3,
      "content_type": 12,
      "object_id": "30",
      "object_repr": "Cart object (30)",
      "action_flag": 3,
      "change_message": ""
    }
  },
  {
    "model": "admin.logentry",
    "pk": 56,
    "fields": {
      "action_time": "2021-07-25T07:00:33.715Z",
      "user": 3,
      "content_type": 12,
      "object_id": "29",
      "object_repr": "Cart object (29)",
      "action_flag": 3,
      "change_message": ""
    }
  },
  {
    "model": "admin.logentry",
    "pk": 57,
    "fields": {
      "action_time": "2021-07-25T07:00:33.750Z",
      "user": 3,
      "content_type": 12,
      "object_id": "28",
      "object_repr": "Cart object (28)",
      "action_flag": 3,
      "change_message": ""
    }
  },
  {
    "model": "admin.logentry",
    "pk": 58,
    "fields": {
      "action_time": "2021-07-25T07:10:05.377Z",
      "user": 3,
      "content_type": 10,
      "object_id": "8",
      "object_repr": "Order object (8)",
      "action_flag": 3,
      "change_message": ""
    }
  },
  {
    "model": "admin.logentry",
    "pk": 59,
    "fields": {
      "action_time": "2021-07-25T07:12:23.855Z",
      "user": 3,
      "content_type": 12,
      "object_id": "33",
      "object_repr": "Cart object (33)",
      "action_flag": 3,
      "change_message": ""
    }
  },
  {
    "model": "admin.logentry",
    "pk": 60,
    "fields": {
      "action_time": "2021-07-25T07:12:23.975Z",
      "user": 3,
      "content_type": 12,
      "object_id": "32",
      "object_repr": "Cart object (32)",
      "action_flag": 3,
      "change_message": ""
    }
  },
  {
    "model": "admin.logentry",
    "pk": 61,
    "fields": {
      "action_time": "2021-07-25T07:13:03.191Z",
      "user": 3,
      "content_type": 12,
      "object_id": "34",
      "object_repr": "Cart object (34)",
      "action_flag": 3,
      "change_message": ""
    }
  },
  {
    "model": "admin.logentry",
    "pk": 62,
    "fields": {
      "action_time": "2021-07-25T07:13:13.767Z",
      "user": 3,
      "content_type": 10,
      "object_id": "9",
      "object_repr": "Order object (9)",
      "action_flag": 3,
      "change_message": ""
    }
  },
  {
    "model": "admin.logentry",
    "pk": 63,
    "fields": {
      "action_time": "2021-07-25T07:14:24.642Z",
      "user": 3,
      "content_type": 10,
      "object_id": "10",
      "object_repr": "Order object (10)",
      "action_flag": 3,
      "change_message": ""
    }
  },
  {
    "model": "admin.logentry",
    "pk": 64,
    "fields": {
      "action_time": "2021-07-25T07:14:29.653Z",
      "user": 3,
      "content_type": 12,
      "object_id": "39",
      "object_repr": "Cart object (39)",
      "action_flag": 3,
      "change_message": ""
    }
  },
  {
    "model": "admin.logentry",
    "pk": 65,
    "fields": {
      "action_time": "2021-07-25T07:14:29.744Z",
      "user": 3,
      "content_type": 12,
      "object_id": "38",
      "object_repr": "Cart object (38)",
      "action_flag": 3,
      "change_message": ""
    }
  },
  {
    "model": "admin.logentry",
    "pk": 66,
    "fields": {
      "action_time": "2021-07-25T07:14:29.780Z",
      "user": 3,
      "content_type": 12,
      "object_id": "37",
      "object_repr": "Cart object (37)",
      "action_flag": 3,
      "change_message": ""
    }
  },
  {
    "model": "admin.logentry",
    "pk": 67,
    "fields": {
      "action_time": "2021-07-25T07:14:29.816Z",
      "user": 3,
      "content_type": 12,
      "object_id": "36",
      "object_repr": "Cart object (36)",
      "action_flag": 3,
      "change_message": ""
    }
  },
  {
    "model": "admin.logentry",
    "pk": 68,
    "fields": {
      "action_time": "2021-07-25T07:14:29.851Z",
      "user": 3,
      "content_type": 12,
      "object_id": "35",
      "object_repr": "Cart object (35)",
      "action_flag": 3,
      "change_message": ""
    }
  },
  {
    "model": "admin.logentry",
    "pk": 69,
    "fields": {
      "action_time": "2021-07-25T07:16:02.490Z",
      "user": 3,
      "content_type": 12,
      "object_id": "50",
      "object_repr": "Cart object (50)",
      "action_flag": 3,
      "change_message": ""
    }
  },
  {
    "model": "admin.logentry",
    "pk": 70,
    "fields": {
      "action_time": "2021-07-25T07:16:02.602Z",
      "user": 3,
      "content_type": 12,
      "object_id": "49",
      "object_repr": "Cart object (49)",
      "action_flag": 3,
      "change_message": ""
    }
  },
  {
    "model": "admin.logentry",
    "pk": 71,
    "fields": {
      "action_time": "2021-07-25T07:16:02.639Z",
      "user": 3,
      "content_type": 12,
      "object_id": "48",
      "object_repr": "Cart object (48)",
      "action_flag": 3,
      "change_message": ""
    }
  },
  {
    "model": "admin.logentry",
    "pk": 72,
    "fields": {
      "action_time": "2021-07-25T07:16:02.675Z",
      "user": 3,
      "content_type": 12,
      "object_id": "47",
      "object_repr": "Cart object (47)",
      "action_flag": 3,
      "change_message": ""
    }
  },
  {
    "model": "admin.logentry",
    "pk": 73,
    "fields": {
      "action_time": "2021-07-25T07:16:02.710Z",
      "user": 3,
      "content_type": 12,
      "object_id": "46",
      "object_repr": "Cart object (46)",
      "action_flag": 3,
      "change_message": ""
    }
  },
  {
    "model": "admin.logentry",
    "pk": 74,
    "fields": {
      "action_time": "2021-07-25T07:16:02.756Z",
      "user": 3,
      "content_type": 12,
      "object_id": "45",
      "object_repr": "Cart object (45)",
      "action_flag": 3,
      "change_message": ""
    }
  },
  {
    "model": "admin.logentry",
    "pk": 75,
    "fields": {
      "action_time": "2021-07-25T07:16:02.792Z",
      "user": 3,
      "content_type": 12,
      "object_id": "44",
      "object_repr": "Cart object (44)",
      "action_flag": 3,
      "change_message": ""
    }
  },
  {
    "model": "admin.logentry",
    "pk": 76,
    "fields": {
      "action_time": "2021-07-25T07:16:02.829Z",
      "user": 3,
      "content_type": 12,
      "object_id": "43",
      "object_repr": "Cart object (43)",
      "action_flag": 3,
      "change_message": ""
    }
  },
  {
    "model": "admin.logentry",
    "pk": 77,
    "fields": {
      "action_time": "2021-07-25T07:16:02.864Z",
      "user": 3,
      "content_type": 12,
      "object_id": "42",
      "object_repr": "Cart object (42)",
      "action_flag": 3,
      "change_message": ""
    }
  },
  {
    "model": "admin.logentry",
    "pk": 78,
    "fields": {
      "action_time": "2021-07-25T07:16:02.900Z",
      "user": 3,
      "content_type": 12,
      "object_id": "41",
      "object_repr": "Cart object (41)",
      "action_flag": 3,
      "change_message": ""
    }
  },
  {
    "model": "admin.logentry",
    "pk": 79,
    "fields": {
      "action_time": "2021-07-25T07:16:02.935Z",
      "user": 3,
      "content_type": 12,
      "object_id": "40",
      "object_repr": "Cart object (40)",
      "action_flag": 3,
      "change_message": ""
    }
  },
  {
    "model": "admin.logentry",
    "pk": 80,
    "fields": {
      "action_time": "2021-07-25T07:16:14.219Z",
      "user": 3,
      "content_type": 10,
      "object_id": "11",
      "object_repr": "Order object (11)",
      "action_flag": 3,
      "change_message": ""
    }
  },
  {
    "model": "admin.logentry",
    "pk": 81,
    "fields": {
      "action_time": "2021-07-25T07:20:28.506Z",
      "user": 3,
      "content_type": 10,
      "object_id": "12",
      "object_repr": "Order object (12)",
      "action_flag": 2,
      "change_message": "[{\"changed\": {\"fields\": [\"Coupon\"]}}]"
    }
  },
  {
    "model": "admin.logentry",
    "pk": 82,
    "fields": {
      "action_time": "2021-07-25T07:21:27.925Z",
      "user": 3,
      "content_type": 10,
      "object_id": "12",
      "object_repr": "Order object (12)",
      "action_flag": 2,
      "change_message": "[{\"changed\": {\"fields\": [\"Coupon\"]}}]"
    }
  },
  {
    "model": "admin.logentry",
    "pk": 83,
    "fields": {
      "action_time": "2021-07-25T07:29:28.812Z",
      "user": 3,
      "content_type": 10,
      "object_id": "12",
      "object_repr": "Order object (12)",
      "action_flag": 2,
      "change_message": "[{\"changed\": {\"fields\": [\"Coupon\"]}}]"
    }
  },
  {
    "model": "admin.logentry",
    "pk": 84,
    "fields": {
      "action_time": "2021-07-25T07:30:05.874Z",
      "user": 3,
      "content_type": 29,
      "object_id": "1",
      "object_repr": "ABC_50",
      "action_flag": 2,
      "change_message": "[{\"changed\": {\"fields\": [\"Valid to\"]}}]"
    }
  },
  {
    "model": "admin.logentry",
    "pk": 85,
    "fields": {
      "action_time": "2021-07-25T07:39:46.037Z",
      "user": 3,
      "content_type": 10,
      "object_id": "12",
      "object_repr": "Order object (12)",
      "action_flag": 2,
      "change_message": "[{\"changed\": {\"fields\": [\"Coupon\"]}}]"
    }
  },
  {
    "model": "admin.logentry",
    "pk": 86,
    "fields": {
      "action_time": "2021-07-25T07:40:06.422Z",
      "user": 3,
      "content_type": 10,
      "object_id": "12",
      "object_repr": "Order object (12)",
      "action_flag": 2,
      "change_message": "[{\"changed\": {\"fields\": [\"Coupon\"]}}]"
    }
  },
  {
    "model": "admin.logentry",
    "pk": 87,
    "fields": {
      "action_time": "2021-07-25T07:41:49.551Z",
      "user": 3,
      "content_type": 10,
      "object_id": "12",
      "object_repr": "Order object (12)",
      "action_flag": 2,
      "change_message": "[{\"changed\": {\"fields\": [\"Coupon\"]}}]"
    }
  },
  {
    "model": "admin.logentry",
    "pk": 88,
    "fields": {
      "action_time": "2021-07-25T07:50:39.932Z",
      "user": 3,
      "content_type": 10,
      "object_id": "12",
      "object_repr": "Order object (12)",
      "action_flag": 2,
      "change_message": "[{\"changed\": {\"fields\": [\"Coupon\"]}}]"
    }
  },
  {
    "model": "admin.logentry",
    "pk": 89,
    "fields": {
      "action_time": "2021-07-25T07:53:53.715Z",
      "user": 3,
      "content_type": 10,
      "object_id": "12",
      "object_repr": "Order object (12)",
      "action_flag": 2,
      "change_message": "[{\"changed\": {\"fields\": [\"Coupon\"]}}]"
    }
  },
  {
    "model": "admin.logentry",
    "pk": 90,
    "fields": {
      "action_time": "2021-07-25T07:59:37.880Z",
      "user": 3,
      "content_type": 10,
      "object_id": "12",
      "object_repr": "Order object (12)",
      "action_flag": 2,
      "change_message": "[{\"changed\": {\"fields\": [\"Coupon\"]}}]"
    }
  },
  {
    "model": "admin.logentry",
    "pk": 91,
    "fields": {
      "action_time": "2021-07-25T08:00:38.008Z",
      "user": 3,
      "content_type": 10,
      "object_id": "12",
      "object_repr": "Order object (12)",
      "action_flag": 2,
      "change_message": "[{\"changed\": {\"fields\": [\"Coupon\"]}}]"
    }
  },
  {
    "model": "admin.logentry",
    "pk": 92,
    "fields": {
      "action_time": "2021-07-25T08:24:12.037Z",
      "user": 3,
      "content_type": 10,
      "object_id": "13",
      "object_repr": "Order object (13)",
      "action_flag": 2,
      "change_message": "[{\"changed\": {\"fields\": [\"Address\"]}}]"
    }
  },
  {
    "model": "admin.logentry",
    "pk": 93,
    "fields": {
      "action_time": "2021-07-25T08:24:50.663Z",
      "user": 3,
      "content_type": 10,
      "object_id": "13",
      "object_repr": "Order object (13)",
      "action_flag": 2,
      "change_message": "[{\"changed\": {\"fields\": [\"Delivery charge\"]}}]"
    }
  },
  {
    "model": "admin.logentry",
    "pk": 94,
    "fields": {
      "action_time": "2021-07-25T10:03:34.493Z",
      "user": 3,
      "content_type": 11,
      "object_id": "1",
      "object_repr": "inside",
      "action_flag": 3,
      "change_message": ""
    }
  },
  {
    "model": "admin.logentry",
    "pk": 95,
    "fields": {
      "action_time": "2021-07-25T10:05:18.387Z",
      "user": 3,
      "content_type": 12,
      "object_id": "72",
      "object_repr": "Cart object (72)",
      "action_flag": 3,
      "change_message": ""
    }
  },
  {
    "model": "admin.logentry",
    "pk": 96,
    "fields": {
      "action_time": "2021-07-25T10:05:18.546Z",
      "user": 3,
      "content_type": 12,
      "object_id": "71",
      "object_repr": "Cart object (71)",
      "action_flag": 3,
      "change_message": ""
    }
  },
  {
    "model": "admin.logentry",
    "pk": 97,
    "fields": {
      "action_time": "2021-07-25T10:05:18.582Z",
      "user": 3,
      "content_type": 12,
      "object_id": "70",
      "object_repr": "Cart object (70)",
      "action_flag": 3,
      "change_message": ""
    }
  },
  {
    "model": "admin.logentry",
    "pk": 98,
    "fields": {
      "action_time": "2021-07-25T10:05:18.618Z",
      "user": 3,
      "content_type": 12,
      "object_id": "69",
      "object_repr": "Cart object (69)",
      "action_flag": 3,
      "change_message": ""
    }
  },
  {
    "model": "admin.logentry",
    "pk": 99,
    "fields": {
      "action_time": "2021-07-25T10:05:18.654Z",
      "user": 3,
      "content_type": 12,
      "object_id": "68",
      "object_repr": "Cart object (68)",
      "action_flag": 3,
      "change_message": ""
    }
  },
  {
    "model": "admin.logentry",
    "pk": 100,
    "fields": {
      "action_time": "2021-07-25T10:05:18.688Z",
      "user": 3,
      "content_type": 12,
      "object_id": "67",
      "object_repr": "Cart object (67)",
      "action_flag": 3,
      "change_message": ""
    }
  },
  {
    "model": "admin.logentry",
    "pk": 101,
    "fields": {
      "action_time": "2021-07-25T10:05:18.723Z",
      "user": 3,
      "content_type": 12,
      "object_id": "66",
      "object_repr": "Cart object (66)",
      "action_flag": 3,
      "change_message": ""
    }
  },
  {
    "model": "admin.logentry",
    "pk": 102,
    "fields": {
      "action_time": "2021-07-25T10:05:18.759Z",
      "user": 3,
      "content_type": 12,
      "object_id": "52",
      "object_repr": "Cart object (52)",
      "action_flag": 3,
      "change_message": ""
    }
  },
  {
    "model": "admin.logentry",
    "pk": 103,
    "fields": {
      "action_time": "2021-07-25T10:05:18.796Z",
      "user": 3,
      "content_type": 12,
      "object_id": "51",
      "object_repr": "Cart object (51)",
      "action_flag": 3,
      "change_message": ""
    }
  },
  {
    "model": "admin.logentry",
    "pk": 104,
    "fields": {
      "action_time": "2021-07-25T10:05:55.141Z",
      "user": 3,
      "content_type": 12,
      "object_id": "73",
      "object_repr": "Cart object (73)",
      "action_flag": 3,
      "change_message": ""
    }
  },
  {
    "model": "admin.logentry",
    "pk": 105,
    "fields": {
      "action_time": "2021-07-25T10:06:01.636Z",
      "user": 3,
      "content_type": 10,
      "object_id": "14",
      "object_repr": "Order object (14)",
      "action_flag": 3,
      "change_message": ""
    }
  },
  {
    "model": "admin.logentry",
    "pk": 106,
    "fields": {
      "action_time": "2021-07-25T10:06:36.818Z",
      "user": 3,
      "content_type": 11,
      "object_id": "2",
      "object_repr": "Address object (2)",
      "action_flag": 3,
      "change_message": ""
    }
  },
  {
    "model": "admin.logentry",
    "pk": 107,
    "fields": {
      "action_time": "2021-07-25T15:22:33.676Z",
      "user": 3,
      "content_type": 10,
      "object_id": "16",
      "object_repr": "Order object (16)",
      "action_flag": 3,
      "change_message": ""
    }
  },
  {
    "model": "admin.logentry",
    "pk": 108,
    "fields": {
      "action_time": "2021-07-25T15:22:33.722Z",
      "user": 3,
      "content_type": 10,
      "object_id": "15",
      "object_repr": "Order object (15)",
      "action_flag": 3,
      "change_message": ""
    }
  },
  {
    "model": "admin.logentry",
    "pk": 109,
    "fields": {
      "action_time": "2021-07-25T15:22:38.597Z",
      "user": 3,
      "content_type": 12,
      "object_id": "75",
      "object_repr": "Cart object (75)",
      "action_flag": 3,
      "change_message": ""
    }
  },
  {
    "model": "admin.logentry",
    "pk": 110,
    "fields": {
      "action_time": "2021-07-25T15:22:38.652Z",
      "user": 3,
      "content_type": 12,
      "object_id": "74",
      "object_repr": "Cart object (74)",
      "action_flag": 3,
      "change_message": ""
    }
  },
  {
    "model": "admin.logentry",
    "pk": 111,
    "fields": {
      "action_time": "2021-07-25T15:24:15.253Z",
      "user": 3,
      "content_type": 10,
      "object_id": "17",
      "object_repr": "Order object (17)",
      "action_flag": 2,
      "change_message": "[]"
    }
  },
  {
    "model": "admin.logentry",
    "pk": 112,
    "fields": {
      "action_time": "2021-07-25T15:25:07.596Z",
      "user": 3,
      "content_type": 10,
      "object_id": "17",
      "object_repr": "Order object (17)",
      "action_flag": 2,
      "change_message": "[]"
    }
  },
  {
    "model": "admin.logentry",
    "pk": 113,
    "fields": {
      "action_time": "2021-07-25T15:26:13.648Z",
      "user": 3,
      "content_type": 12,
      "object_id": "81",
      "object_repr": "Cart object (81)",
      "action_flag": 3,
      "change_message": ""
    }
  },
  {
    "model": "admin.logentry",
    "pk": 114,
    "fields": {
      "action_time": "2021-07-25T15:26:13.693Z",
      "user": 3,
      "content_type": 12,
      "object_id": "80",
      "object_repr": "Cart object (80)",
      "action_flag": 3,
      "change_message": ""
    }
  },
  {
    "model": "admin.logentry",
    "pk": 115,
    "fields": {
      "action_time": "2021-07-25T15:26:13.751Z",
      "user": 3,
      "content_type": 12,
      "object_id": "79",
      "object_repr": "Cart object (79)",
      "action_flag": 3,
      "change_message": ""
    }
  },
  {
    "model": "admin.logentry",
    "pk": 116,
    "fields": {
      "action_time": "2021-07-25T15:26:13.797Z",
      "user": 3,
      "content_type": 12,
      "object_id": "78",
      "object_repr": "Cart object (78)",
      "action_flag": 3,
      "change_message": ""
    }
  },
  {
    "model": "admin.logentry",
    "pk": 117,
    "fields": {
      "action_time": "2021-07-25T15:26:13.843Z",
      "user": 3,
      "content_type": 12,
      "object_id": "77",
      "object_repr": "Cart object (77)",
      "action_flag": 3,
      "change_message": ""
    }
  },
  {
    "model": "admin.logentry",
    "pk": 118,
    "fields": {
      "action_time": "2021-07-25T15:26:13.890Z",
      "user": 3,
      "content_type": 12,
      "object_id": "76",
      "object_repr": "Cart object (76)",
      "action_flag": 3,
      "change_message": ""
    }
  },
  {
    "model": "admin.logentry",
    "pk": 119,
    "fields": {
      "action_time": "2021-07-25T15:26:19.854Z",
      "user": 3,
      "content_type": 10,
      "object_id": "17",
      "object_repr": "Order object (17)",
      "action_flag": 3,
      "change_message": ""
    }
  },
  {
    "model": "admin.logentry",
    "pk": 120,
    "fields": {
      "action_time": "2021-07-25T15:27:34.086Z",
      "user": 3,
      "content_type": 10,
      "object_id": "18",
      "object_repr": "Order object (18)",
      "action_flag": 3,
      "change_message": ""
    }
  },
  {
    "model": "admin.logentry",
    "pk": 121,
    "fields": {
      "action_time": "2021-07-25T15:28:09.698Z",
      "user": 3,
      "content_type": 10,
      "object_id": "19",
      "object_repr": "Order object (19)",
      "action_flag": 3,
      "change_message": ""
    }
  },
  {
    "model": "admin.logentry",
    "pk": 122,
    "fields": {
      "action_time": "2021-07-25T15:28:15.559Z",
      "user": 3,
      "content_type": 12,
      "object_id": "83",
      "object_repr": "Cart object (83)",
      "action_flag": 3,
      "change_message": ""
    }
  },
  {
    "model": "admin.logentry",
    "pk": 123,
    "fields": {
      "action_time": "2021-07-25T15:28:15.609Z",
      "user": 3,
      "content_type": 12,
      "object_id": "82",
      "object_repr": "Cart object (82)",
      "action_flag": 3,
      "change_message": ""
    }
  },
  {
    "model": "admin.logentry",
    "pk": 124,
    "fields": {
      "action_time": "2021-07-25T15:30:49.818Z",
      "user": 3,
      "content_type": 10,
      "object_id": "20",
      "object_repr": "Order object (20)",
      "action_flag": 2,
      "change_message": "[]"
    }
  },
  {
    "model": "admin.logentry",
    "pk": 125,
    "fields": {
      "action_time": "2021-07-25T15:30:57.696Z",
      "user": 3,
      "content_type": 10,
      "object_id": "20",
      "object_repr": "Order object (20)",
      "action_flag": 3,
      "change_message": ""
    }
  },
  {
    "model": "admin.logentry",
    "pk": 126,
    "fields": {
      "action_time": "2021-07-25T15:31:03.276Z",
      "user": 3,
      "content_type": 12,
      "object_id": "89",
      "object_repr": "Cart object (89)",
      "action_flag": 3,
      "change_message": ""
    }
  },
  {
    "model": "admin.logentry",
    "pk": 127,
    "fields": {
      "action_time": "2021-07-25T15:31:03.332Z",
      "user": 3,
      "content_type": 12,
      "object_id": "88",
      "object_repr": "Cart object (88)",
      "action_flag": 3,
      "change_message": ""
    }
  },
  {
    "model": "admin.logentry",
    "pk": 128,
    "fields": {
      "action_time": "2021-07-25T15:31:03.390Z",
      "user": 3,
      "content_type": 12,
      "object_id": "87",
      "object_repr": "Cart object (87)",
      "action_flag": 3,
      "change_message": ""
    }
  },
  {
    "model": "admin.logentry",
    "pk": 129,
    "fields": {
      "action_time": "2021-07-25T15:31:03.436Z",
      "user": 3,
      "content_type": 12,
      "object_id": "86",
      "object_repr": "Cart object (86)",
      "action_flag": 3,
      "change_message": ""
    }
  },
  {
    "model": "admin.logentry",
    "pk": 130,
    "fields": {
      "action_time": "2021-07-25T15:31:03.483Z",
      "user": 3,
      "content_type": 12,
      "object_id": "85",
      "object_repr": "Cart object (85)",
      "action_flag": 3,
      "change_message": ""
    }
  },
  {
    "model": "admin.logentry",
    "pk": 131,
    "fields": {
      "action_time": "2021-07-25T15:31:03.540Z",
      "user": 3,
      "content_type": 12,
      "object_id": "84",
      "object_repr": "Cart object (84)",
      "action_flag": 3,
      "change_message": ""
    }
  },
  {
    "model": "admin.logentry",
    "pk": 132,
    "fields": {
      "action_time": "2021-07-25T15:31:34.612Z",
      "user": 3,
      "content_type": 10,
      "object_id": "21",
      "object_repr": "Order object (21)",
      "action_flag": 2,
      "change_message": "[]"
    }
  },
  {
    "model": "admin.logentry",
    "pk": 133,
    "fields": {
      "action_time": "2021-07-25T15:32:03.055Z",
      "user": 3,
      "content_type": 10,
      "object_id": "21",
      "object_repr": "Order object (21)",
      "action_flag": 3,
      "change_message": ""
    }
  },
  {
    "model": "admin.logentry",
    "pk": 134,
    "fields": {
      "action_time": "2021-07-25T15:32:22.059Z",
      "user": 3,
      "content_type": 10,
      "object_id": "22",
      "object_repr": "Order object (22)",
      "action_flag": 3,
      "change_message": ""
    }
  },
  {
    "model": "admin.logentry",
    "pk": 135,
    "fields": {
      "action_time": "2021-07-25T15:32:27.903Z",
      "user": 3,
      "content_type": 12,
      "object_id": "93",
      "object_repr": "Cart object (93)",
      "action_flag": 3,
      "change_message": ""
    }
  },
  {
    "model": "admin.logentry",
    "pk": 136,
    "fields": {
      "action_time": "2021-07-25T15:32:27.952Z",
      "user": 3,
      "content_type": 12,
      "object_id": "92",
      "object_repr": "Cart object (92)",
      "action_flag": 3,
      "change_message": ""
    }
  },
  {
    "model": "admin.logentry",
    "pk": 137,
    "fields": {
      "action_time": "2021-07-25T15:32:27.999Z",
      "user": 3,
      "content_type": 12,
      "object_id": "91",
      "object_repr": "Cart object (91)",
      "action_flag": 3,
      "change_message": ""
    }
  },
  {
    "model": "admin.logentry",
    "pk": 138,
    "fields": {
      "action_time": "2021-07-25T15:32:28.056Z",
      "user": 3,
      "content_type": 12,
      "object_id": "90",
      "object_repr": "Cart object (90)",
      "action_flag": 3,
      "change_message": ""
    }
  },
  {
    "model": "admin.logentry",
    "pk": 139,
    "fields": {
      "action_time": "2021-07-25T15:32:53.007Z",
      "user": 3,
      "content_type": 10,
      "object_id": "23",
      "object_repr": "Order object (23)",
      "action_flag": 3,
      "change_message": ""
    }
  },
  {
    "model": "admin.logentry",
    "pk": 140,
    "fields": {
      "action_time": "2021-07-25T15:32:59.674Z",
      "user": 3,
      "content_type": 12,
      "object_id": "94",
      "object_repr": "Cart object (94)",
      "action_flag": 3,
      "change_message": ""
    }
  },
  {
    "model": "auth.permission",
    "pk": 1,
    "fields": {
      "name": "Can add log entry",
      "content_type": 1,
      "codename": "add_logentry"
    }
  },
  {
    "model": "auth.permission",
    "pk": 2,
    "fields": {
      "name": "Can change log entry",
      "content_type": 1,
      "codename": "change_logentry"
    }
  },
  {
    "model": "auth.permission",
    "pk": 3,
    "fields": {
      "name": "Can delete log entry",
      "content_type": 1,
      "codename": "delete_logentry"
    }
  },
  {
    "model": "auth.permission",
    "pk": 4,
    "fields": {
      "name": "Can view log entry",
      "content_type": 1,
      "codename": "view_logentry"
    }
  },
  {
    "model": "auth.permission",
    "pk": 5,
    "fields": {
      "name": "Can add permission",
      "content_type": 2,
      "codename": "add_permission"
    }
  },
  {
    "model": "auth.permission",
    "pk": 6,
    "fields": {
      "name": "Can change permission",
      "content_type": 2,
      "codename": "change_permission"
    }
  },
  {
    "model": "auth.permission",
    "pk": 7,
    "fields": {
      "name": "Can delete permission",
      "content_type": 2,
      "codename": "delete_permission"
    }
  },
  {
    "model": "auth.permission",
    "pk": 8,
    "fields": {
      "name": "Can view permission",
      "content_type": 2,
      "codename": "view_permission"
    }
  },
  {
    "model": "auth.permission",
    "pk": 9,
    "fields": {
      "name": "Can add group",
      "content_type": 3,
      "codename": "add_group"
    }
  },
  {
    "model": "auth.permission",
    "pk": 10,
    "fields": {
      "name": "Can change group",
      "content_type": 3,
      "codename": "change_group"
    }
  },
  {
    "model": "auth.permission",
    "pk": 11,
    "fields": {
      "name": "Can delete group",
      "content_type": 3,
      "codename": "delete_group"
    }
  },
  {
    "model": "auth.permission",
    "pk": 12,
    "fields": {
      "name": "Can view group",
      "content_type": 3,
      "codename": "view_group"
    }
  },
  {
    "model": "auth.permission",
    "pk": 13,
    "fields": {
      "name": "Can add content type",
      "content_type": 4,
      "codename": "add_contenttype"
    }
  },
  {
    "model": "auth.permission",
    "pk": 14,
    "fields": {
      "name": "Can change content type",
      "content_type": 4,
      "codename": "change_contenttype"
    }
  },
  {
    "model": "auth.permission",
    "pk": 15,
    "fields": {
      "name": "Can delete content type",
      "content_type": 4,
      "codename": "delete_contenttype"
    }
  },
  {
    "model": "auth.permission",
    "pk": 16,
    "fields": {
      "name": "Can view content type",
      "content_type": 4,
      "codename": "view_contenttype"
    }
  },
  {
    "model": "auth.permission",
    "pk": 17,
    "fields": {
      "name": "Can add session",
      "content_type": 5,
      "codename": "add_session"
    }
  },
  {
    "model": "auth.permission",
    "pk": 18,
    "fields": {
      "name": "Can change session",
      "content_type": 5,
      "codename": "change_session"
    }
  },
  {
    "model": "auth.permission",
    "pk": 19,
    "fields": {
      "name": "Can delete session",
      "content_type": 5,
      "codename": "delete_session"
    }
  },
  {
    "model": "auth.permission",
    "pk": 20,
    "fields": {
      "name": "Can view session",
      "content_type": 5,
      "codename": "view_session"
    }
  },
  {
    "model": "auth.permission",
    "pk": 21,
    "fields": {
      "name": "Can add Product",
      "content_type": 6,
      "codename": "add_products"
    }
  },
  {
    "model": "auth.permission",
    "pk": 22,
    "fields": {
      "name": "Can change Product",
      "content_type": 6,
      "codename": "change_products"
    }
  },
  {
    "model": "auth.permission",
    "pk": 23,
    "fields": {
      "name": "Can delete Product",
      "content_type": 6,
      "codename": "delete_products"
    }
  },
  {
    "model": "auth.permission",
    "pk": 24,
    "fields": {
      "name": "Can view Product",
      "content_type": 6,
      "codename": "view_products"
    }
  },
  {
    "model": "auth.permission",
    "pk": 25,
    "fields": {
      "name": "Can add product images",
      "content_type": 7,
      "codename": "add_productimages"
    }
  },
  {
    "model": "auth.permission",
    "pk": 26,
    "fields": {
      "name": "Can change product images",
      "content_type": 7,
      "codename": "change_productimages"
    }
  },
  {
    "model": "auth.permission",
    "pk": 27,
    "fields": {
      "name": "Can delete product images",
      "content_type": 7,
      "codename": "delete_productimages"
    }
  },
  {
    "model": "auth.permission",
    "pk": 28,
    "fields": {
      "name": "Can view product images",
      "content_type": 7,
      "codename": "view_productimages"
    }
  },
  {
    "model": "auth.permission",
    "pk": 29,
    "fields": {
      "name": "Can add user",
      "content_type": 8,
      "codename": "add_user"
    }
  },
  {
    "model": "auth.permission",
    "pk": 30,
    "fields": {
      "name": "Can change user",
      "content_type": 8,
      "codename": "change_user"
    }
  },
  {
    "model": "auth.permission",
    "pk": 31,
    "fields": {
      "name": "Can delete user",
      "content_type": 8,
      "codename": "delete_user"
    }
  },
  {
    "model": "auth.permission",
    "pk": 32,
    "fields": {
      "name": "Can view user",
      "content_type": 8,
      "codename": "view_user"
    }
  },
  {
    "model": "auth.permission",
    "pk": 33,
    "fields": {
      "name": "Can add wish list",
      "content_type": 9,
      "codename": "add_wishlist"
    }
  },
  {
    "model": "auth.permission",
    "pk": 34,
    "fields": {
      "name": "Can change wish list",
      "content_type": 9,
      "codename": "change_wishlist"
    }
  },
  {
    "model": "auth.permission",
    "pk": 35,
    "fields": {
      "name": "Can delete wish list",
      "content_type": 9,
      "codename": "delete_wishlist"
    }
  },
  {
    "model": "auth.permission",
    "pk": 36,
    "fields": {
      "name": "Can view wish list",
      "content_type": 9,
      "codename": "view_wishlist"
    }
  },
  {
    "model": "auth.permission",
    "pk": 37,
    "fields": {
      "name": "Can add order",
      "content_type": 10,
      "codename": "add_order"
    }
  },
  {
    "model": "auth.permission",
    "pk": 38,
    "fields": {
      "name": "Can change order",
      "content_type": 10,
      "codename": "change_order"
    }
  },
  {
    "model": "auth.permission",
    "pk": 39,
    "fields": {
      "name": "Can delete order",
      "content_type": 10,
      "codename": "delete_order"
    }
  },
  {
    "model": "auth.permission",
    "pk": 40,
    "fields": {
      "name": "Can view order",
      "content_type": 10,
      "codename": "view_order"
    }
  },
  {
    "model": "auth.permission",
    "pk": 41,
    "fields": {
      "name": "Can add address",
      "content_type": 11,
      "codename": "add_address"
    }
  },
  {
    "model": "auth.permission",
    "pk": 42,
    "fields": {
      "name": "Can change address",
      "content_type": 11,
      "codename": "change_address"
    }
  },
  {
    "model": "auth.permission",
    "pk": 43,
    "fields": {
      "name": "Can delete address",
      "content_type": 11,
      "codename": "delete_address"
    }
  },
  {
    "model": "auth.permission",
    "pk": 44,
    "fields": {
      "name": "Can view address",
      "content_type": 11,
      "codename": "view_address"
    }
  },
  {
    "model": "auth.permission",
    "pk": 45,
    "fields": {
      "name": "Can add cart",
      "content_type": 12,
      "codename": "add_cart"
    }
  },
  {
    "model": "auth.permission",
    "pk": 46,
    "fields": {
      "name": "Can change cart",
      "content_type": 12,
      "codename": "change_cart"
    }
  },
  {
    "model": "auth.permission",
    "pk": 47,
    "fields": {
      "name": "Can delete cart",
      "content_type": 12,
      "codename": "delete_cart"
    }
  },
  {
    "model": "auth.permission",
    "pk": 48,
    "fields": {
      "name": "Can view cart",
      "content_type": 12,
      "codename": "view_cart"
    }
  },
  {
    "model": "auth.permission",
    "pk": 49,
    "fields": {
      "name": "Can add order item",
      "content_type": 13,
      "codename": "add_orderitem"
    }
  },
  {
    "model": "auth.permission",
    "pk": 50,
    "fields": {
      "name": "Can change order item",
      "content_type": 13,
      "codename": "change_orderitem"
    }
  },
  {
    "model": "auth.permission",
    "pk": 51,
    "fields": {
      "name": "Can delete order item",
      "content_type": 13,
      "codename": "delete_orderitem"
    }
  },
  {
    "model": "auth.permission",
    "pk": 52,
    "fields": {
      "name": "Can view order item",
      "content_type": 13,
      "codename": "view_orderitem"
    }
  },
  {
    "model": "auth.permission",
    "pk": 53,
    "fields": {
      "name": "Can add recently view",
      "content_type": 14,
      "codename": "add_recentlyview"
    }
  },
  {
    "model": "auth.permission",
    "pk": 54,
    "fields": {
      "name": "Can change recently view",
      "content_type": 14,
      "codename": "change_recentlyview"
    }
  },
  {
    "model": "auth.permission",
    "pk": 55,
    "fields": {
      "name": "Can delete recently view",
      "content_type": 14,
      "codename": "delete_recentlyview"
    }
  },
  {
    "model": "auth.permission",
    "pk": 56,
    "fields": {
      "name": "Can view recently view",
      "content_type": 14,
      "codename": "view_recentlyview"
    }
  },
  {
    "model": "auth.permission",
    "pk": 57,
    "fields": {
      "name": "Can add application",
      "content_type": 15,
      "codename": "add_application"
    }
  },
  {
    "model": "auth.permission",
    "pk": 58,
    "fields": {
      "name": "Can change application",
      "content_type": 15,
      "codename": "change_application"
    }
  },
  {
    "model": "auth.permission",
    "pk": 59,
    "fields": {
      "name": "Can delete application",
      "content_type": 15,
      "codename": "delete_application"
    }
  },
  {
    "model": "auth.permission",
    "pk": 60,
    "fields": {
      "name": "Can view application",
      "content_type": 15,
      "codename": "view_application"
    }
  },
  {
    "model": "auth.permission",
    "pk": 61,
    "fields": {
      "name": "Can add access token",
      "content_type": 16,
      "codename": "add_accesstoken"
    }
  },
  {
    "model": "auth.permission",
    "pk": 62,
    "fields": {
      "name": "Can change access token",
      "content_type": 16,
      "codename": "change_accesstoken"
    }
  },
  {
    "model": "auth.permission",
    "pk": 63,
    "fields": {
      "name": "Can delete access token",
      "content_type": 16,
      "codename": "delete_accesstoken"
    }
  },
  {
    "model": "auth.permission",
    "pk": 64,
    "fields": {
      "name": "Can view access token",
      "content_type": 16,
      "codename": "view_accesstoken"
    }
  },
  {
    "model": "auth.permission",
    "pk": 65,
    "fields": {
      "name": "Can add grant",
      "content_type": 17,
      "codename": "add_grant"
    }
  },
  {
    "model": "auth.permission",
    "pk": 66,
    "fields": {
      "name": "Can change grant",
      "content_type": 17,
      "codename": "change_grant"
    }
  },
  {
    "model": "auth.permission",
    "pk": 67,
    "fields": {
      "name": "Can delete grant",
      "content_type": 17,
      "codename": "delete_grant"
    }
  },
  {
    "model": "auth.permission",
    "pk": 68,
    "fields": {
      "name": "Can view grant",
      "content_type": 17,
      "codename": "view_grant"
    }
  },
  {
    "model": "auth.permission",
    "pk": 69,
    "fields": {
      "name": "Can add refresh token",
      "content_type": 18,
      "codename": "add_refreshtoken"
    }
  },
  {
    "model": "auth.permission",
    "pk": 70,
    "fields": {
      "name": "Can change refresh token",
      "content_type": 18,
      "codename": "change_refreshtoken"
    }
  },
  {
    "model": "auth.permission",
    "pk": 71,
    "fields": {
      "name": "Can delete refresh token",
      "content_type": 18,
      "codename": "delete_refreshtoken"
    }
  },
  {
    "model": "auth.permission",
    "pk": 72,
    "fields": {
      "name": "Can view refresh token",
      "content_type": 18,
      "codename": "view_refreshtoken"
    }
  },
  {
    "model": "auth.permission",
    "pk": 73,
    "fields": {
      "name": "Can add id token",
      "content_type": 19,
      "codename": "add_idtoken"
    }
  },
  {
    "model": "auth.permission",
    "pk": 74,
    "fields": {
      "name": "Can change id token",
      "content_type": 19,
      "codename": "change_idtoken"
    }
  },
  {
    "model": "auth.permission",
    "pk": 75,
    "fields": {
      "name": "Can delete id token",
      "content_type": 19,
      "codename": "delete_idtoken"
    }
  },
  {
    "model": "auth.permission",
    "pk": 76,
    "fields": {
      "name": "Can view id token",
      "content_type": 19,
      "codename": "view_idtoken"
    }
  },
  {
    "model": "auth.permission",
    "pk": 77,
    "fields": {
      "name": "Can add association",
      "content_type": 20,
      "codename": "add_association"
    }
  },
  {
    "model": "auth.permission",
    "pk": 78,
    "fields": {
      "name": "Can change association",
      "content_type": 20,
      "codename": "change_association"
    }
  },
  {
    "model": "auth.permission",
    "pk": 79,
    "fields": {
      "name": "Can delete association",
      "content_type": 20,
      "codename": "delete_association"
    }
  },
  {
    "model": "auth.permission",
    "pk": 80,
    "fields": {
      "name": "Can view association",
      "content_type": 20,
      "codename": "view_association"
    }
  },
  {
    "model": "auth.permission",
    "pk": 81,
    "fields": {
      "name": "Can add code",
      "content_type": 21,
      "codename": "add_code"
    }
  },
  {
    "model": "auth.permission",
    "pk": 82,
    "fields": {
      "name": "Can change code",
      "content_type": 21,
      "codename": "change_code"
    }
  },
  {
    "model": "auth.permission",
    "pk": 83,
    "fields": {
      "name": "Can delete code",
      "content_type": 21,
      "codename": "delete_code"
    }
  },
  {
    "model": "auth.permission",
    "pk": 84,
    "fields": {
      "name": "Can view code",
      "content_type": 21,
      "codename": "view_code"
    }
  },
  {
    "model": "auth.permission",
    "pk": 85,
    "fields": {
      "name": "Can add nonce",
      "content_type": 22,
      "codename": "add_nonce"
    }
  },
  {
    "model": "auth.permission",
    "pk": 86,
    "fields": {
      "name": "Can change nonce",
      "content_type": 22,
      "codename": "change_nonce"
    }
  },
  {
    "model": "auth.permission",
    "pk": 87,
    "fields": {
      "name": "Can delete nonce",
      "content_type": 22,
      "codename": "delete_nonce"
    }
  },
  {
    "model": "auth.permission",
    "pk": 88,
    "fields": {
      "name": "Can view nonce",
      "content_type": 22,
      "codename": "view_nonce"
    }
  },
  {
    "model": "auth.permission",
    "pk": 89,
    "fields": {
      "name": "Can add user social auth",
      "content_type": 23,
      "codename": "add_usersocialauth"
    }
  },
  {
    "model": "auth.permission",
    "pk": 90,
    "fields": {
      "name": "Can change user social auth",
      "content_type": 23,
      "codename": "change_usersocialauth"
    }
  },
  {
    "model": "auth.permission",
    "pk": 91,
    "fields": {
      "name": "Can delete user social auth",
      "content_type": 23,
      "codename": "delete_usersocialauth"
    }
  },
  {
    "model": "auth.permission",
    "pk": 92,
    "fields": {
      "name": "Can view user social auth",
      "content_type": 23,
      "codename": "view_usersocialauth"
    }
  },
  {
    "model": "auth.permission",
    "pk": 93,
    "fields": {
      "name": "Can add partial",
      "content_type": 24,
      "codename": "add_partial"
    }
  },
  {
    "model": "auth.permission",
    "pk": 94,
    "fields": {
      "name": "Can change partial",
      "content_type": 24,
      "codename": "change_partial"
    }
  },
  {
    "model": "auth.permission",
    "pk": 95,
    "fields": {
      "name": "Can delete partial",
      "content_type": 24,
      "codename": "delete_partial"
    }
  },
  {
    "model": "auth.permission",
    "pk": 96,
    "fields": {
      "name": "Can view partial",
      "content_type": 24,
      "codename": "view_partial"
    }
  },
  {
    "model": "auth.permission",
    "pk": 97,
    "fields": {
      "name": "Can add Token",
      "content_type": 25,
      "codename": "add_token"
    }
  },
  {
    "model": "auth.permission",
    "pk": 98,
    "fields": {
      "name": "Can change Token",
      "content_type": 25,
      "codename": "change_token"
    }
  },
  {
    "model": "auth.permission",
    "pk": 99,
    "fields": {
      "name": "Can delete Token",
      "content_type": 25,
      "codename": "delete_token"
    }
  },
  {
    "model": "auth.permission",
    "pk": 100,
    "fields": {
      "name": "Can view Token",
      "content_type": 25,
      "codename": "view_token"
    }
  },
  {
    "model": "auth.permission",
    "pk": 101,
    "fields": {
      "name": "Can add token",
      "content_type": 26,
      "codename": "add_tokenproxy"
    }
  },
  {
    "model": "auth.permission",
    "pk": 102,
    "fields": {
      "name": "Can change token",
      "content_type": 26,
      "codename": "change_tokenproxy"
    }
  },
  {
    "model": "auth.permission",
    "pk": 103,
    "fields": {
      "name": "Can delete token",
      "content_type": 26,
      "codename": "delete_tokenproxy"
    }
  },
  {
    "model": "auth.permission",
    "pk": 104,
    "fields": {
      "name": "Can view token",
      "content_type": 26,
      "codename": "view_tokenproxy"
    }
  },
  {
    "model": "auth.permission",
    "pk": 105,
    "fields": {
      "name": "Can add Callback Token",
      "content_type": 27,
      "codename": "add_callbacktoken"
    }
  },
  {
    "model": "auth.permission",
    "pk": 106,
    "fields": {
      "name": "Can change Callback Token",
      "content_type": 27,
      "codename": "change_callbacktoken"
    }
  },
  {
    "model": "auth.permission",
    "pk": 107,
    "fields": {
      "name": "Can delete Callback Token",
      "content_type": 27,
      "codename": "delete_callbacktoken"
    }
  },
  {
    "model": "auth.permission",
    "pk": 108,
    "fields": {
      "name": "Can view Callback Token",
      "content_type": 27,
      "codename": "view_callbacktoken"
    }
  },
  {
    "model": "auth.permission",
    "pk": 109,
    "fields": {
      "name": "Can add OTP Token",
      "content_type": 28,
      "codename": "add_phonetoken"
    }
  },
  {
    "model": "auth.permission",
    "pk": 110,
    "fields": {
      "name": "Can change OTP Token",
      "content_type": 28,
      "codename": "change_phonetoken"
    }
  },
  {
    "model": "auth.permission",
    "pk": 111,
    "fields": {
      "name": "Can delete OTP Token",
      "content_type": 28,
      "codename": "delete_phonetoken"
    }
  },
  {
    "model": "auth.permission",
    "pk": 112,
    "fields": {
      "name": "Can view OTP Token",
      "content_type": 28,
      "codename": "view_phonetoken"
    }
  },
  {
    "model": "auth.permission",
    "pk": 113,
    "fields": {
      "name": "Can add coupon",
      "content_type": 29,
      "codename": "add_coupon"
    }
  },
  {
    "model": "auth.permission",
    "pk": 114,
    "fields": {
      "name": "Can change coupon",
      "content_type": 29,
      "codename": "change_coupon"
    }
  },
  {
    "model": "auth.permission",
    "pk": 115,
    "fields": {
      "name": "Can delete coupon",
      "content_type": 29,
      "codename": "delete_coupon"
    }
  },
  {
    "model": "auth.permission",
    "pk": 116,
    "fields": {
      "name": "Can view coupon",
      "content_type": 29,
      "codename": "view_coupon"
    }
  },
  {
    "model": "auth.permission",
    "pk": 117,
    "fields": {
      "name": "Can add delivery charge",
      "content_type": 30,
      "codename": "add_deliverycharge"
    }
  },
  {
    "model": "auth.permission",
    "pk": 118,
    "fields": {
      "name": "Can change delivery charge",
      "content_type": 30,
      "codename": "change_deliverycharge"
    }
  },
  {
    "model": "auth.permission",
    "pk": 119,
    "fields": {
      "name": "Can delete delivery charge",
      "content_type": 30,
      "codename": "delete_deliverycharge"
    }
  },
  {
    "model": "auth.permission",
    "pk": 120,
    "fields": {
      "name": "Can view delivery charge",
      "content_type": 30,
      "codename": "view_deliverycharge"
    }
  },
  {
    "model": "contenttypes.contenttype",
    "pk": 1,
    "fields": { "app_label": "admin", "model": "logentry" }
  },
  {
    "model": "contenttypes.contenttype",
    "pk": 2,
    "fields": { "app_label": "auth", "model": "permission" }
  },
  {
    "model": "contenttypes.contenttype",
    "pk": 3,
    "fields": { "app_label": "auth", "model": "group" }
  },
  {
    "model": "contenttypes.contenttype",
    "pk": 4,
    "fields": { "app_label": "contenttypes", "model": "contenttype" }
  },
  {
    "model": "contenttypes.contenttype",
    "pk": 5,
    "fields": { "app_label": "sessions", "model": "session" }
  },
  {
    "model": "contenttypes.contenttype",
    "pk": 6,
    "fields": { "app_label": "products", "model": "products" }
  },
  {
    "model": "contenttypes.contenttype",
    "pk": 7,
    "fields": { "app_label": "products", "model": "productimages" }
  },
  {
    "model": "contenttypes.contenttype",
    "pk": 8,
    "fields": { "app_label": "users", "model": "user" }
  },
  {
    "model": "contenttypes.contenttype",
    "pk": 9,
    "fields": { "app_label": "wishlist", "model": "wishlist" }
  },
  {
    "model": "contenttypes.contenttype",
    "pk": 10,
    "fields": { "app_label": "orders", "model": "order" }
  },
  {
    "model": "contenttypes.contenttype",
    "pk": 11,
    "fields": { "app_label": "address", "model": "address" }
  },
  {
    "model": "contenttypes.contenttype",
    "pk": 12,
    "fields": { "app_label": "cart", "model": "cart" }
  },
  {
    "model": "contenttypes.contenttype",
    "pk": 13,
    "fields": { "app_label": "cart", "model": "orderitem" }
  },
  {
    "model": "contenttypes.contenttype",
    "pk": 14,
    "fields": { "app_label": "cart", "model": "recentlyview" }
  },
  {
    "model": "contenttypes.contenttype",
    "pk": 15,
    "fields": { "app_label": "oauth2_provider", "model": "application" }
  },
  {
    "model": "contenttypes.contenttype",
    "pk": 16,
    "fields": { "app_label": "oauth2_provider", "model": "accesstoken" }
  },
  {
    "model": "contenttypes.contenttype",
    "pk": 17,
    "fields": { "app_label": "oauth2_provider", "model": "grant" }
  },
  {
    "model": "contenttypes.contenttype",
    "pk": 18,
    "fields": { "app_label": "oauth2_provider", "model": "refreshtoken" }
  },
  {
    "model": "contenttypes.contenttype",
    "pk": 19,
    "fields": { "app_label": "oauth2_provider", "model": "idtoken" }
  },
  {
    "model": "contenttypes.contenttype",
    "pk": 20,
    "fields": { "app_label": "social_django", "model": "association" }
  },
  {
    "model": "contenttypes.contenttype",
    "pk": 21,
    "fields": { "app_label": "social_django", "model": "code" }
  },
  {
    "model": "contenttypes.contenttype",
    "pk": 22,
    "fields": { "app_label": "social_django", "model": "nonce" }
  },
  {
    "model": "contenttypes.contenttype",
    "pk": 23,
    "fields": { "app_label": "social_django", "model": "usersocialauth" }
  },
  {
    "model": "contenttypes.contenttype",
    "pk": 24,
    "fields": { "app_label": "social_django", "model": "partial" }
  },
  {
    "model": "contenttypes.contenttype",
    "pk": 25,
    "fields": { "app_label": "authtoken", "model": "token" }
  },
  {
    "model": "contenttypes.contenttype",
    "pk": 26,
    "fields": { "app_label": "authtoken", "model": "tokenproxy" }
  },
  {
    "model": "contenttypes.contenttype",
    "pk": 27,
    "fields": { "app_label": "drfpasswordless", "model": "callbacktoken" }
  },
  {
    "model": "contenttypes.contenttype",
    "pk": 28,
    "fields": { "app_label": "phone_login", "model": "phonetoken" }
  },
  {
    "model": "contenttypes.contenttype",
    "pk": 29,
    "fields": { "app_label": "coupon", "model": "coupon" }
  },
  {
    "model": "contenttypes.contenttype",
    "pk": 30,
    "fields": { "app_label": "orders", "model": "deliverycharge" }
  },
  {
    "model": "sessions.session",
    "pk": "r3ridpahellk4t67rbqy1xf1oadeobkc",
    "fields": {
      "session_data": ".eJxVjEEOwiAQRe_C2hDI1MK49ATegAwMI42GGmlXxrsbIgtdvvfz30sF2rcS9pafYWF1UlYdfl2kdMu1D4-y1hzu63Wpetimv3KgvnQ6j8dfplArPW6NQSEQM0ueMVuTZYLkOHqTnACjTM4eIzoWj4TCAI4ZojgPAKTeH5eBOuE:1m4nTv:hNWujs6OJhULxGKLYibCBNQPsW59Gz4NxdULuAa842A",
      "expire_date": "2021-07-31T16:48:03.533Z"
    }
  },
  {
    "model": "sessions.session",
    "pk": "tq1reb4ypn6gkyzscvn3gyhdcg30ytxy",
    "fields": {
      "session_data": ".eJxVjDsOwjAQBe_iGln-41DS5wzW2ruLA8iR4qRC3B0ipYD2zcx7iQTbWtPWaUkTiouw4vS7ZSgPajvAO7TbLMvc1mXKclfkQbscZ6Tn9XD_Dir0-q0HHbMDbwIxFwzB6BKZlSUCZ7wGtCazPrsQrcuFwQBrHnwmhYiWlXh_APvmOOY:1m4lR8:2fQu9O-471Wnmrz2EizNYMBRv3sbJ_0W7L9Hu7b8LEw",
      "expire_date": "2021-07-31T14:37:02.088Z"
    }
  },
  {
    "model": "sessions.session",
    "pk": "vvikx83ph5n4v8pxwhciufj5ui0bloce",
    "fields": {
      "session_data": ".eJxVjEsOAiEQBe_C2hD-Ay49gTcgDd3IRMMYcVbGuxsiC11Wvbx6sQj7s8a90yOuyI7MsMOvS5Cv1MZwr1ujeNsua-PTdv6VE_l50Gk-_jIVeh1xUiEYQrCqEBmZtc6LTOgBvMjCSFfABa9lQMAiVJIhOWcMkl3Ao2XvD6AnOs4:1m4na8:2k1cB2qqgSDGk94SqEskl1U6fhZHWGik0vAksi7qGHI",
      "expire_date": "2021-07-31T16:54:28.892Z"
    }
  },
  {
    "model": "products.products",
    "pk": 1,
    "fields": {
      "name": "md sohan",
      "slug": "md-sohan",
      "category": "hair_care",
      "thumbnail": "",
      "short_desc": "551715551715551715551715",
      "description": "551715551715551715551715551715551715551715551715551715551715551715551715551715551715551715551715551715551715551715551715",
      "manufacturer": null,
      "country_made": null,
      "benifits": null,
      "price": 11,
      "discount_price": 6,
      "timestamp": "2021-07-17T16:49:56.404Z",
      "best_selling": true,
      "featured": true,
      "trending": true,
      "quantity_in_stock": null,
      "out_of_stock": false,
      "s_size": false,
      "m_size": true,
      "l_size": true,
      "xl_size": true,
      "xxl_size": true,
      "product_delivery_time": 2
    }
  },
  {
    "model": "products.products",
    "pk": 2,
    "fields": {
      "name": "one",
      "slug": "one",
      "category": "hair_care",
      "thumbnail": "thumbnail/15_ucuz4sj.webp",
      "short_desc": "PRODUCT DESCRIPTION",
      "description": "PRODUCT DESCRIPTION\r\n\r\nGo high on style and comfort with these Batman AOP Superhero Men's Flip-Flops. Style these flip-flops with a t-shirt and a pair of trousers for a cool look.\r\nCountry of Origin : India",
      "manufacturer": null,
      "country_made": null,
      "benifits": null,
      "price": 14,
      "discount_price": 7,
      "timestamp": "2021-07-23T16:09:44.909Z",
      "best_selling": true,
      "featured": true,
      "trending": true,
      "quantity_in_stock": null,
      "out_of_stock": false,
      "s_size": true,
      "m_size": false,
      "l_size": true,
      "xl_size": true,
      "xxl_size": true,
      "product_delivery_time": 2
    }
  },
  {
    "model": "products.products",
    "pk": 3,
    "fields": {
      "name": "two",
      "slug": "two",
      "category": null,
      "thumbnail": "thumbnail/9_iF7ZB4t.webp",
      "short_desc": "PRODUCT DESCRIPTION\r\n\r\nGo high on style and comfort with these Batman AOP Superhero Men's Flip-Flops. Style these flip-flops with a t-shirt and a pair of trousers for a cool look.\r\nCountry of Origin : India",
      "description": "PRODUCT DESCRIPTION\r\n\r\nGo high on style and comfort with these Batman AOP Superhero Men's Flip-Flops. Style these flip-flops with a t-shirt and a pair of trousers for a cool look.\r\nCountry of Origin : India",
      "manufacturer": null,
      "country_made": null,
      "benifits": null,
      "price": 3,
      "discount_price": 1,
      "timestamp": "2021-07-23T16:10:15.599Z",
      "best_selling": false,
      "featured": true,
      "trending": true,
      "quantity_in_stock": null,
      "out_of_stock": false,
      "s_size": false,
      "m_size": true,
      "l_size": true,
      "xl_size": true,
      "xxl_size": false,
      "product_delivery_time": 2
    }
  },
  {
    "model": "products.products",
    "pk": 4,
    "fields": {
      "name": "three",
      "slug": "three",
      "category": "hair_care",
      "thumbnail": "thumbnail/14_BHAAdvV.webp",
      "short_desc": "",
      "description": "",
      "manufacturer": null,
      "country_made": null,
      "benifits": null,
      "price": 13,
      "discount_price": 2,
      "timestamp": "2021-07-23T16:10:41.554Z",
      "best_selling": true,
      "featured": false,
      "trending": true,
      "quantity_in_stock": null,
      "out_of_stock": false,
      "s_size": true,
      "m_size": true,
      "l_size": true,
      "xl_size": true,
      "xxl_size": true,
      "product_delivery_time": 2
    }
  },
  {
    "model": "products.products",
    "pk": 5,
    "fields": {
      "name": "four",
      "slug": "four",
      "category": null,
      "thumbnail": "thumbnail/9_9HMnD16.webp",
      "short_desc": "PRODUCT DESCRIPTION\r\n\r\nGo high on style and comfort with these Batman AOP Superhero Men's Flip-Flops. Style these flip-flops with a t-shirt and a pair of trousers for a cool look.\r\nCountry of Origin : India",
      "description": "PRODUCT DESCRIPTION\r\n\r\nGo high on style and comfort with these Batman AOP Superhero Men's Flip-Flops. Style these flip-flops with a t-shirt and a pair of trousers for a cool look.\r\nCountry of Origin : India",
      "manufacturer": null,
      "country_made": null,
      "benifits": null,
      "price": 2,
      "discount_price": 2,
      "timestamp": "2021-07-23T16:11:11.976Z",
      "best_selling": false,
      "featured": true,
      "trending": true,
      "quantity_in_stock": null,
      "out_of_stock": false,
      "s_size": true,
      "m_size": true,
      "l_size": true,
      "xl_size": true,
      "xxl_size": false,
      "product_delivery_time": 2
    }
  },
  {
    "model": "products.products",
    "pk": 6,
    "fields": {
      "name": "seven",
      "slug": "seven",
      "category": "hair_care",
      "thumbnail": "thumbnail/6_C1GCHmM.webp",
      "short_desc": "PRODUCT DESCRIPTION\r\n\r\nGo high on style and comfort with these Batman AOP Superhero Men's Flip-Flops. Style these flip-flops with a t-shirt and a pair of trousers for a cool look.\r\nCountry of Origin : India",
      "description": "PRODUCT DESCRIPTION\r\n\r\nGo high on style and comfort with these Batman AOP Superhero Men's Flip-Flops. Style these flip-flops with a t-shirt and a pair of trousers for a cool look.\r\nCountry of Origin : India",
      "manufacturer": null,
      "country_made": null,
      "benifits": null,
      "price": 10,
      "discount_price": 3,
      "timestamp": "2021-07-23T16:11:39.657Z",
      "best_selling": false,
      "featured": false,
      "trending": true,
      "quantity_in_stock": null,
      "out_of_stock": false,
      "s_size": false,
      "m_size": true,
      "l_size": true,
      "xl_size": true,
      "xxl_size": false,
      "product_delivery_time": 2
    }
  },
  {
    "model": "products.productimages",
    "pk": 1,
    "fields": { "product": 1, "image": "product-details/5_JAxnXWf.webp" }
  },
  {
    "model": "products.productimages",
    "pk": 2,
    "fields": { "product": 1, "image": "product-details/11_imNkxlW.webp" }
  },
  {
    "model": "products.productimages",
    "pk": 3,
    "fields": { "product": 1, "image": "product-details/1_iqVyyfZ.webp" }
  },
  {
    "model": "products.productimages",
    "pk": 4,
    "fields": { "product": 2, "image": "product-details/8_wCClaq2.webp" }
  },
  {
    "model": "products.productimages",
    "pk": 5,
    "fields": { "product": 2, "image": "product-details/10_EdYG0u2.webp" }
  },
  {
    "model": "products.productimages",
    "pk": 6,
    "fields": { "product": 2, "image": "product-details/5_BXwyDmQ.webp" }
  },
  {
    "model": "products.productimages",
    "pk": 7,
    "fields": { "product": 3, "image": "product-details/3_HfN3uIZ.webp" }
  },
  {
    "model": "products.productimages",
    "pk": 8,
    "fields": { "product": 3, "image": "product-details/12_GMJWXYv.webp" }
  },
  {
    "model": "products.productimages",
    "pk": 9,
    "fields": { "product": 3, "image": "product-details/5_UKg7J4b.webp" }
  },
  {
    "model": "products.productimages",
    "pk": 10,
    "fields": { "product": 4, "image": "product-details/4_eH3ik8s.webp" }
  },
  {
    "model": "products.productimages",
    "pk": 11,
    "fields": { "product": 4, "image": "product-details/12_2STZBBd.webp" }
  },
  {
    "model": "products.productimages",
    "pk": 12,
    "fields": { "product": 4, "image": "product-details/1_2egQbfs.webp" }
  },
  {
    "model": "products.productimages",
    "pk": 13,
    "fields": { "product": 5, "image": "product-details/5_Kt8cGOQ.webp" }
  },
  {
    "model": "products.productimages",
    "pk": 14,
    "fields": { "product": 5, "image": "product-details/6_Znz4T3f.webp" }
  },
  {
    "model": "products.productimages",
    "pk": 15,
    "fields": { "product": 5, "image": "product-details/14_QTHMddi.webp" }
  },
  {
    "model": "products.productimages",
    "pk": 16,
    "fields": { "product": 6, "image": "product-details/5_HQTHyny.webp" }
  },
  {
    "model": "products.productimages",
    "pk": 17,
    "fields": { "product": 6, "image": "product-details/7_mryXFHq.webp" }
  },
  {
    "model": "products.productimages",
    "pk": 18,
    "fields": { "product": 6, "image": "product-details/4_7wePwNp.webp" }
  },
  {
    "model": "users.user",
    "pk": 1,
    "fields": {
      "password": "pbkdf2_sha256$260000$zi3ulDdFep9CauJLR5vcJd$cRQ/qRMeICuR8WQszrYHuacG92B1eta6rieG6n2l7XU=",
      "last_login": "2021-07-17T16:48:03.449Z",
      "is_superuser": true,
      "first_name": "",
      "last_name": "",
      "email": "",
      "is_staff": true,
      "is_active": true,
      "date_joined": "2021-07-17T14:28:56.159Z",
      "phone_number": "+8801786910645",
      "username": "sohan",
      "groups": [],
      "user_permissions": []
    }
  },
  {
    "model": "users.user",
    "pk": 2,
    "fields": {
      "password": "pbkdf2_sha256$260000$Sm4Vbh9gqFgpUGn6iJ7TA1$hRkAAS5gsKCIrjwLa29jzDB8CO7tcYZkiSkgv2p9cJs=",
      "last_login": "2021-07-17T14:31:27.537Z",
      "is_superuser": false,
      "first_name": "",
      "last_name": "",
      "email": "",
      "is_staff": false,
      "is_active": true,
      "date_joined": "2021-07-17T14:29:48.355Z",
      "phone_number": "+8801786910644",
      "username": "fc3db544-9032-4a9a-90b4-a5397569e4ac",
      "groups": [],
      "user_permissions": []
    }
  },
  {
    "model": "users.user",
    "pk": 3,
    "fields": {
      "password": "pbkdf2_sha256$260000$OG5noCfvNDpCJ4mAPOyGIk$udNeDCenpfN9Ii6UR+I1BccGOgZ3OO5oYe+JLb2XiZ8=",
      "last_login": "2021-07-17T14:37:02.006Z",
      "is_superuser": true,
      "first_name": "",
      "last_name": "",
      "email": "",
      "is_staff": true,
      "is_active": true,
      "date_joined": "2021-07-17T14:36:36.006Z",
      "phone_number": "+8801784291133",
      "username": "sohan",
      "groups": [],
      "user_permissions": []
    }
  },
  {
    "model": "users.user",
    "pk": 4,
    "fields": {
      "password": "pbkdf2_sha256$260000$OpZiQWrzrSp8Vy2V4Oo2Bh$VCFMizX5yqff+Op+F5+O6U10J+m8Do1o5Sec5QzLgh4=",
      "last_login": "2021-07-17T16:54:28.821Z",
      "is_superuser": false,
      "first_name": "",
      "last_name": "",
      "email": "",
      "is_staff": false,
      "is_active": true,
      "date_joined": "2021-07-17T16:54:28.356Z",
      "phone_number": "+8801786910688",
      "username": "1b6eadb8-991f-40f8-a8b2-a198935ebde1",
      "groups": [],
      "user_permissions": []
    }
  },
  {
    "model": "orders.deliverycharge",
    "pk": 1,
    "fields": { "location": "inside_dhaka", "delivery_charge": 60 }
  },
  {
    "model": "orders.deliverycharge",
    "pk": 2,
    "fields": { "location": "outside_dhaka", "delivery_charge": 120 }
  },
  {
    "model": "orders.order",
    "pk": 24,
    "fields": {
      "user": 4,
      "start_date": "2021-07-25T15:33:03.245Z",
      "ordered_date": "2021-07-25T15:33:03.244Z",
      "coupon": null,
      "sub_total": 0,
      "total": null,
      "ordered": false,
      "address": null,
      "delivery_charge": null,
      "payment_method": null,
      "payment_number": null,
      "being_delivered": false,
      "received": false,
      "refund_requested": false,
      "refund_granted": false,
      "products": [96, 97, 98, 99, 100]
    }
  },
  {
    "model": "address.address",
    "pk": 3,
    "fields": {
      "user": 4,
      "phone_number": null,
      "email": null,
      "street_address": "cvn",
      "zip": "1216",
      "inside_dahaka_or_outside_dhaka": null,
      "district": null
    }
  },
  {
    "model": "cart.cart",
    "pk": 95,
    "fields": {
      "user": 4,
      "product": 5,
      "expires": false,
      "size": "xl",
      "color": null,
      "quantity": 1,
      "timestamp": "2021-07-25T15:33:03.129Z"
    }
  },
  {
    "model": "cart.cart",
    "pk": 96,
    "fields": {
      "user": 4,
      "product": 5,
      "expires": false,
      "size": "xl",
      "color": null,
      "quantity": 1,
      "timestamp": "2021-07-25T15:34:05.759Z"
    }
  },
  {
    "model": "cart.cart",
    "pk": 97,
    "fields": {
      "user": 4,
      "product": 5,
      "expires": false,
      "size": "xl",
      "color": null,
      "quantity": 1,
      "timestamp": "2021-07-25T15:34:14.020Z"
    }
  },
  {
    "model": "cart.cart",
    "pk": 98,
    "fields": {
      "user": 4,
      "product": 5,
      "expires": false,
      "size": "xl",
      "color": null,
      "quantity": 1,
      "timestamp": "2021-07-25T15:34:15.182Z"
    }
  },
  {
    "model": "cart.cart",
    "pk": 99,
    "fields": {
      "user": 4,
      "product": 5,
      "expires": false,
      "size": "xl",
      "color": null,
      "quantity": 1,
      "timestamp": "2021-07-25T15:34:17.366Z"
    }
  },
  {
    "model": "cart.cart",
    "pk": 100,
    "fields": {
      "user": 4,
      "product": 5,
      "expires": false,
      "size": "xl",
      "color": null,
      "quantity": 1,
      "timestamp": "2021-07-25T15:34:15.183Z"
    }
  },
  {
    "model": "coupon.coupon",
    "pk": 1,
    "fields": {
      "code": "ABC_50",
      "valid_from": "2021-07-24T08:26:05Z",
      "valid_to": "2021-07-26T08:25:12Z",
      "discount_amount": 50,
      "number_of_use": 1,
      "active": true
    }
  },
  {
    "model": "authtoken.token",
    "pk": "8b3b2dec62027ca4d859b600bd491fdfc480f31e",
    "fields": { "user": 4, "created": "2021-07-17T16:54:28.858Z" }
  },
  {
    "model": "authtoken.token",
    "pk": "a270d0a0c92aa1c6a6809b3d888654d1f55adba9",
    "fields": { "user": 1, "created": "2021-07-17T16:48:03.490Z" }
  },
  {
    "model": "authtoken.token",
    "pk": "b464a01dd16e216102a21c399eca6331a289f000",
    "fields": { "user": 2, "created": "2021-07-17T14:29:50.559Z" }
  },
  {
    "model": "phone_login.phonetoken",
    "pk": 1,
    "fields": {
      "phone_number": "+8801786910644",
      "otp": "153684",
      "timestamp": "2021-07-17T14:29:30.929Z",
      "attempts": 1,
      "used": true
    }
  },
  {
    "model": "phone_login.phonetoken",
    "pk": 2,
    "fields": {
      "phone_number": "+8801786910644",
      "otp": "633509",
      "timestamp": "2021-07-17T14:30:51.822Z",
      "attempts": 1,
      "used": true
    }
  },
  {
    "model": "phone_login.phonetoken",
    "pk": 3,
    "fields": {
      "phone_number": "+8801786910644",
      "otp": "995212",
      "timestamp": "2021-07-17T14:31:13.669Z",
      "attempts": 2,
      "used": true
    }
  },
  {
    "model": "phone_login.phonetoken",
    "pk": 4,
    "fields": {
      "phone_number": "+8801786910644",
      "otp": "604907",
      "timestamp": "2021-07-17T15:01:06.694Z",
      "attempts": 0,
      "used": false
    }
  },
  {
    "model": "phone_login.phonetoken",
    "pk": 5,
    "fields": {
      "phone_number": "+8801786910645",
      "otp": "495843",
      "timestamp": "2021-07-17T16:42:12.441Z",
      "attempts": 0,
      "used": false
    }
  },
  {
    "model": "phone_login.phonetoken",
    "pk": 6,
    "fields": {
      "phone_number": "+8801786910645",
      "otp": "346458",
      "timestamp": "2021-07-17T16:42:44.622Z",
      "attempts": 0,
      "used": false
    }
  },
  {
    "model": "phone_login.phonetoken",
    "pk": 7,
    "fields": {
      "phone_number": "+8801786910645",
      "otp": "755533",
      "timestamp": "2021-07-17T16:44:00.231Z",
      "attempts": 0,
      "used": false
    }
  },
  {
    "model": "phone_login.phonetoken",
    "pk": 8,
    "fields": {
      "phone_number": "+8801786910645",
      "otp": "234320",
      "timestamp": "2021-07-17T16:44:37.760Z",
      "attempts": 0,
      "used": false
    }
  },
  {
    "model": "phone_login.phonetoken",
    "pk": 9,
    "fields": {
      "phone_number": "+8801786910645",
      "otp": "551715",
      "timestamp": "2021-07-17T16:45:05.774Z",
      "attempts": 1,
      "used": true
    }
  },
  {
    "model": "phone_login.phonetoken",
    "pk": 10,
    "fields": {
      "phone_number": "+8801786910688",
      "otp": "826147",
      "timestamp": "2021-07-17T16:54:11.636Z",
      "attempts": 1,
      "used": true
    }
  },
  {
    "model": "phone_login.phonetoken",
    "pk": 11,
    "fields": {
      "phone_number": "+8801786910645",
      "otp": "427941",
      "timestamp": "2021-07-17T17:14:04.940Z",
      "attempts": 0,
      "used": false
    }
  }
]
